README
setup.py
lava_test_demo/__init__.py
lava_test_demo/tests.py
lava_test_demo.egg-info/PKG-INFO
lava_test_demo.egg-info/SOURCES.txt
lava_test_demo.egg-info/dependency_links.txt
lava_test_demo.egg-info/entry_points.txt
lava_test_demo.egg-info/not-zip-safe
lava_test_demo.egg-info/requires.txt
lava_test_demo.egg-info/top_level.txt