Metadata-Version: 1.0
Name: lava-test-demo
Version: 0.1.dev7
Summary: Demonstration test for LAVA
Home-page: https://code.launchpad.net/~zkrynicki/+junk/lava-demo-test
Author: Zygmunt Krynicki
Author-email: linaro-dev@lists.linaro.org
License: GNU GPLv3
Platform: UNKNOWN
Classifier: Development Status :: 3 - Alpha
Classifier: Intended Audience :: Developers
Classifier: License :: OSI Approved :: GNU General Public License (GPL)
Classifier: Operating System :: OS Independent
Classifier: Programming Language :: Python :: 2.6
Classifier: Programming Language :: Python :: 2.7
Classifier: Topic :: Software Development :: Testing
